gluoncvth/__init__.py
gluoncvth/models/__init__.py
gluoncvth/models/base.py
gluoncvth/models/deeplab.py
gluoncvth/models/fcn.py
gluoncvth/models/model_store.py
gluoncvth/models/model_zoo.py
gluoncvth/models/pspnet.py
gluoncvth/models/resnet.py
gluoncvth/models/wideresnet.py
gluoncvth/utils/__init__.py
gluoncvth/utils/files.py
gluoncvth/utils/pallete.py
gluoncvth/utils/preset.py
gluoncv_torch-0.0.5.dist-info/LICENSE
gluoncv_torch-0.0.5.dist-info/METADATA
gluoncv_torch-0.0.5.dist-info/WHEEL
gluoncv_torch-0.0.5.dist-info/top_level.txt
gluoncv_torch-0.0.5.dist-info/zip-safe
gluoncv_torch-0.0.5.dist-info/RECORD
