Metadata-Version: 2.1
Name: gluoncv-torch
Version: 0.0.5
Summary: MXNet Gluon CV Toolkit
Home-page: https://github.com/dmlc/gluon-cv
Author: Gluon CV Toolkit Contributors
License: Apache-2.0
Platform: UNKNOWN
Requires-Dist: numpy
Requires-Dist: torch
Requires-Dist: tqdm
Requires-Dist: request
Requires-Dist: Pillow
